mclang_compiler-0.3.4.dist-info/WHEEL
mclang_compiler-0.3.4.dist-info/entry_points.txt
mclang_compiler-0.3.4.dist-info/METADATA
mclang_compiler/mcc/__init__.py
mclang_compiler/mcc/__main__.py
mclang_compiler/mcc/bin/_codecs_cn.so
mclang_compiler/mcc/bin/_codecs_kr.so
mclang_compiler/mcc/bin/_sha1.so
mclang_compiler/mcc/bin/grp.so
mclang_compiler/mcc/bin/_statistics.so
mclang_compiler/mcc/bin/_heapq.so
mclang_compiler/mcc/bin/_codecs_tw.so
mclang_compiler/mcc/bin/_opcode.so
mclang_compiler/mcc/bin/_codecs_hk.so
mclang_compiler/mcc/bin/_blake2.so
mclang_compiler/mcc/bin/_lzma.so
mclang_compiler/mcc/bin/math.so
mclang_compiler/mcc/bin/_contextvars.so
mclang_compiler/mcc/bin/_csv.so
mclang_compiler/mcc/bin/libbz2.so.1.0
mclang_compiler/mcc/bin/_posixsubprocess.so
mclang_compiler/mcc/bin/zlib.so
mclang_compiler/mcc/bin/_bz2.so
mclang_compiler/mcc/bin/_codecs_iso2022.so
mclang_compiler/mcc/bin/_datetime.so
mclang_compiler/mcc/bin/_codecs_jp.so
mclang_compiler/mcc/bin/unicodedata.so
mclang_compiler/mcc/bin/binascii.so
mclang_compiler/mcc/bin/_socket.so
mclang_compiler/mcc/bin/liblzma.so.5
mclang_compiler/mcc/bin/fcntl.so
mclang_compiler/mcc/bin/_random.so
mclang_compiler/mcc/bin/_sha2.so
mclang_compiler/mcc/bin/_sha3.so
mclang_compiler/mcc/bin/_md5.so
mclang_compiler/mcc/bin/select.so
mclang_compiler/mcc/bin/_multibytecodec.so
mclang_compiler/mcc/bin/mcc.bin
mclang_compiler/mcc/bin/_pickle.so
mclang_compiler/mcc/bin/_struct.so
mclang_compiler/mcc/bin/mcc/passes/group_merge.so
mclang_compiler/mcc/bin/mcc/passes/dataflow_analysis.so
mclang_compiler/mcc/bin/mcc/passes/type_replacement.so
mclang_compiler/mcc/bin/mcc/passes/async_analysis.so
mclang_compiler/mcc/bin/mcc/passes/__init__.so
mclang_compiler/mcc/bin/mcc/passes/base.so
mclang_compiler/mcc/bin/mcc/passes/await_transform.so
mclang_compiler/mcc/bin/mcc/passes/type_inference.so
mclang_compiler/mcc/bin/mcc/passes/declaration_analysis.so
mclang_compiler/mcc/bin/mcc/passes/parameter_analysis.so
mclang_compiler/mcc/bin/mcc/ir/debug.so
mclang_compiler/mcc/bin/mcc/ir/base.so
mclang_compiler/mcc/bin/mcc/ir/utilities.so
mclang_compiler-0.3.4.dist-info/RECORD
