Metadata-Version: 2.1
Name: mclang-compiler
Version: 0.3.4
Summary: MCLang Compiler - Binary Distribution (Linux ARM64)
Author: MCLang Development Team
Author-email: mclang@openubmc.com
License: Mulan PSL v2
Keywords: compiler,code-generator,transpiler
Platform: Linux ARM64
Classifier: Development Status :: 3 - Alpha
Classifier: Intended Audience :: Developers
Classifier: Topic :: Software Development :: Code Generators
Requires-Python: >=3.11
Project-URL: Homepage, https://gitcode.com/openubmc/mcc
Project-URL: Documentation, https://gitcode.com/openubmc/mcc
Project-URL: Repository, https://gitcode.com/openubmc/mcc
Project-URL: Issues, https://gitcode.com/openubmc/mcc/issues
